timeout_iterator/__init__.py
timeout_iterator/_version.py
timeout_iterator/terminate.py
timeout_iterator/without_terminate.py
timeout_iterator-0.2.2.dist-info/LICENSE
timeout_iterator-0.2.2.dist-info/METADATA
timeout_iterator-0.2.2.dist-info/WHEEL
timeout_iterator-0.2.2.dist-info/top_level.txt
timeout_iterator-0.2.2.dist-info/RECORD
